nvdllogger/__init__.py
nvdllogger/logger.py
nvdllogger-1.0.0.dist-info/LICENSE
nvdllogger-1.0.0.dist-info/METADATA
nvdllogger-1.0.0.dist-info/WHEEL
nvdllogger-1.0.0.dist-info/top_level.txt
nvdllogger-1.0.0.dist-info/RECORD
