Metadata-Version: 2.1
Name: nvdllogger
Version: 1.0.0
Summary: NVIDIA DLLogger - logging for Deep Learning applications
Home-page: https://github.com/NVIDIA/dllogger
Author: NVIDIA Corporation
License: Apache2
Classifier: Programming Language :: Python :: 3
Classifier: Programming Language :: Python :: 3.5
Classifier: Programming Language :: Python :: 3.6
Classifier: Programming Language :: Python :: 3.7
Classifier: Operating System :: OS Independent
Requires-Python: >=3.5
License-File: ./LICENSE
